odoo/addons/sale_commitment_lead_time/README.rst
odoo/addons/sale_commitment_lead_time/__init__.py
odoo/addons/sale_commitment_lead_time/__manifest__.py
odoo/addons/sale_commitment_lead_time/i18n/ca.po
odoo/addons/sale_commitment_lead_time/i18n/es.po
odoo/addons/sale_commitment_lead_time/i18n/sale_commitment_lead_time.pot
odoo/addons/sale_commitment_lead_time/models/__init__.py
odoo/addons/sale_commitment_lead_time/models/res_company.py
odoo/addons/sale_commitment_lead_time/models/res_config_settings.py
odoo/addons/sale_commitment_lead_time/models/sale_order.py
odoo/addons/sale_commitment_lead_time/readme/CONFIGURE.rst
odoo/addons/sale_commitment_lead_time/readme/CONTRIBUTORS.rst
odoo/addons/sale_commitment_lead_time/readme/DESCRIPTION.rst
odoo/addons/sale_commitment_lead_time/static/description/icon.png
odoo/addons/sale_commitment_lead_time/static/description/index.html
odoo/addons/sale_commitment_lead_time/tests/__init__.py
odoo/addons/sale_commitment_lead_time/tests/test_sale_order_preparation_time.py
odoo/addons/sale_commitment_lead_time/views/res_config_settings.xml
odoo/addons/sale_commitment_lead_time/views/sale_order.xml
odoo12_addon_sale_commitment_lead_time-12.0.1.0.0.99.dev11.dist-info/METADATA
odoo12_addon_sale_commitment_lead_time-12.0.1.0.0.99.dev11.dist-info/WHEEL
odoo12_addon_sale_commitment_lead_time-12.0.1.0.0.99.dev11.dist-info/top_level.txt
odoo12_addon_sale_commitment_lead_time-12.0.1.0.0.99.dev11.dist-info/RECORD
